{"levelIndex":749,"moveCount":24,"difficulty":0,"stages":[{"objects":[{"tableId":0,"type":1,"size":{"x":1.0,"y":2.0,"z":1.0},"pos":{"x":1.546,"y":1.0,"z":-1.84775925},"rot":{"x":0.0,"y":-0.195090309,"z":0.0,"w":0.98078537}},{"tableId":0,"type":1,"size":{"x":1.0,"y":2.0,"z":1.0},"pos":{"x":1.546,"y":4.0,"z":-1.84775925},"rot":{"x":0.0,"y":-0.195090309,"z":0.0,"w":0.98078537}},{"tableId":0,"type":1,"size":{"x":1.0,"y":2.0,"z":1.0},"pos":{"x":1.546,"y":7.02,"z":-1.84775925},"rot":{"x":0.0,"y":-0.195090309,"z":0.0,"w":0.98078537}},{"tableId":0,"type":1,"size":{"x":1.0,"y":2.0,"z":1.0},"pos":{"x":1.546,"y":1.0,"z":2.0},"rot":{"x":0.0,"y":-0.195090309,"z":0.0,"w":0.98078537}},{"tableId":0,"type":1,"size":{"x":1.0,"y":2.0,"z":1.0},"pos":{"x":1.546,"y":4.0,"z":2.0},"rot":{"x":0.0,"y":-0.195090309,"z":0.0,"w":0.98078537}},{"tableId":0,"type":1,"size":{"x":1.0,"y":2.0,"z":1.0},"pos":{"x":1.546,"y":7.02,"z":2.0},"rot":{"x":0.0,"y":-0.195090309,"z":0.0,"w":0.98078537}},{"tableId":0,"type":1,"size":{"x":1.0,"y":2.0,"z":1.0},"pos":{"x":-1.546,"y":1.0,"z":-1.84775925},"rot":{"x":0.0,"y":-0.195090309,"z":0.0,"w":0.98078537}},{"tableId":0,"type":1,"size":{"x":1.0,"y":2.0,"z":1.0},"pos":{"x":-1.546,"y":4.0,"z":-1.84775925},"rot":{"x":0.0,"y":-0.195090309,"z":0.0,"w":0.98078537}},{"tableId":0,"type":1,"size":{"x":1.0,"y":2.0,"z":1.0},"pos":{"x":-1.546,"y":7.02,"z":-1.84775925},"rot":{"x":0.0,"y":-0.195090309,"z":0.0,"w":0.98078537}},{"tableId":0,"type":1,"size":{"x":1.0,"y":2.0,"z":1.0},"pos":{"x":-1.546,"y":1.0,"z":2.0},"rot":{"x":0.0,"y":-0.195090309,"z":0.0,"w":0.98078537}},{"tableId":0,"type":1,"size":{"x":1.0,"y":2.0,"z":1.0},"pos":{"x":-1.546,"y":4.0,"z":2.0},"rot":{"x":0.0,"y":-0.195090309,"z":0.0,"w":0.98078537}},{"tableId":0,"type":1,"size":{"x":1.0,"y":2.0,"z":1.0},"pos":{"x":-1.546,"y":7.02,"z":2.0},"rot":{"x":0.0,"y":-0.195090309,"z":0.0,"w":0.98078537}},{"tableId":0,"type":1,"size":{"x":1.0,"y":2.0,"z":1.0},"pos":{"x":3.812,"y":1.0,"z":-1.84775925},"rot":{"x":0.0,"y":-0.195090309,"z":0.0,"w":0.98078537}},{"tableId":0,"type":1,"size":{"x":1.0,"y":2.0,"z":1.0},"pos":{"x":3.812,"y":4.0,"z":-1.84775925},"rot":{"x":0.0,"y":-0.195090309,"z":0.0,"w":0.98078537}},{"tableId":0,"type":1,"size":{"x":1.0,"y":2.0,"z":1.0},"pos":{"x":3.812,"y":7.02,"z":-1.84775925},"rot":{"x":0.0,"y":-0.195090309,"z":0.0,"w":0.98078537}},{"tableId":0,"type":1,"size":{"x":1.0,"y":2.0,"z":1.0},"pos":{"x":3.812,"y":1.0,"z":2.0},"rot":{"x":0.0,"y":-0.195090309,"z":0.0,"w":0.98078537}},{"tableId":0,"type":1,"size":{"x":1.0,"y":2.0,"z":1.0},"pos":{"x":3.812,"y":4.0,"z":2.0},"rot":{"x":0.0,"y":-0.195090309,"z":0.0,"w":0.98078537}},{"tableId":0,"type":1,"size":{"x":1.0,"y":2.0,"z":1.0},"pos":{"x":3.812,"y":7.02,"z":2.0},"rot":{"x":0.0,"y":-0.195090309,"z":0.0,"w":0.98078537}},{"tableId":0,"type":1,"size":{"x":1.0,"y":2.0,"z":1.0},"pos":{"x":-3.812,"y":1.0,"z":-1.84775925},"rot":{"x":0.0,"y":-0.195090309,"z":0.0,"w":0.98078537}},{"tableId":0,"type":1,"size":{"x":1.0,"y":2.0,"z":1.0},"pos":{"x":-3.812,"y":4.0,"z":-1.84775925},"rot":{"x":0.0,"y":-0.195090309,"z":0.0,"w":0.98078537}},{"tableId":0,"type":1,"size":{"x":1.0,"y":2.0,"z":1.0},"pos":{"x":-3.812,"y":7.02,"z":-1.84775925},"rot":{"x":0.0,"y":-0.195090309,"z":0.0,"w":0.98078537}},{"tableId":0,"type":1,"size":{"x":1.0,"y":2.0,"z":1.0},"pos":{"x":-3.812,"y":1.0,"z":2.0},"rot":{"x":0.0,"y":-0.195090309,"z":0.0,"w":0.98078537}},{"tableId":0,"type":1,"size":{"x":1.0,"y":2.0,"z":1.0},"pos":{"x":-3.812,"y":4.0,"z":2.0},"rot":{"x":0.0,"y":-0.195090309,"z":0.0,"w":0.98078537}},{"tableId":0,"type":1,"size":{"x":1.0,"y":2.0,"z":1.0},"pos":{"x":-3.812,"y":7.02,"z":2.0},"rot":{"x":0.0,"y":-0.195090309,"z":0.0,"w":0.98078537}},{"tableId":0,"type":3,"size":{"x":3.0,"y":1.0,"z":1.0},"pos":{"x":2.987,"y":2.5,"z":-1.84775925},"rot":{"x":0.0,"y":0.0,"z":0.0,"w":1.0}},{"tableId":0,"type":3,"size":{"x":3.0,"y":1.0,"z":1.0},"pos":{"x":2.987,"y":5.49999952,"z":-1.84775925},"rot":{"x":0.0,"y":0.0,"z":0.0,"w":1.0}},{"tableId":0,"type":3,"size":{"x":3.0,"y":1.0,"z":1.0},"pos":{"x":2.987,"y":8.52,"z":-1.84775925},"rot":{"x":0.0,"y":0.0,"z":0.0,"w":1.0}},{"tableId":0,"type":3,"size":{"x":3.0,"y":1.0,"z":1.0},"pos":{"x":2.987,"y":2.5,"z":2.0},"rot":{"x":0.0,"y":0.0,"z":0.0,"w":1.0}},{"tableId":0,"type":3,"size":{"x":3.0,"y":1.0,"z":1.0},"pos":{"x":2.987,"y":5.49999952,"z":2.0},"rot":{"x":0.0,"y":0.0,"z":0.0,"w":1.0}},{"tableId":0,"type":3,"size":{"x":3.0,"y":1.0,"z":1.0},"pos":{"x":2.987,"y":8.52,"z":2.0},"rot":{"x":0.0,"y":0.0,"z":0.0,"w":1.0}},{"tableId":0,"type":3,"size":{"x":3.0,"y":1.0,"z":1.0},"pos":{"x":-2.987,"y":2.5,"z":-1.84775925},"rot":{"x":0.0,"y":0.0,"z":0.0,"w":1.0}},{"tableId":0,"type":3,"size":{"x":3.0,"y":1.0,"z":1.0},"pos":{"x":-2.987,"y":5.49999952,"z":-1.84775925},"rot":{"x":0.0,"y":0.0,"z":0.0,"w":1.0}},{"tableId":0,"type":3,"size":{"x":3.0,"y":1.0,"z":1.0},"pos":{"x":-2.987,"y":8.52,"z":-1.84775925},"rot":{"x":0.0,"y":0.0,"z":0.0,"w":1.0}},{"tableId":0,"type":3,"size":{"x":3.0,"y":1.0,"z":1.0},"pos":{"x":-2.987,"y":2.5,"z":2.0},"rot":{"x":0.0,"y":0.0,"z":0.0,"w":1.0}},{"tableId":0,"type":3,"size":{"x":3.0,"y":1.0,"z":1.0},"pos":{"x":-2.987,"y":5.49999952,"z":2.0},"rot":{"x":0.0,"y":0.0,"z":0.0,"w":1.0}},{"tableId":0,"type":3,"size":{"x":3.0,"y":1.0,"z":1.0},"pos":{"x":-2.987,"y":8.52,"z":2.0},"rot":{"x":0.0,"y":0.0,"z":0.0,"w":1.0}},{"tableId":0,"type":3,"size":{"x":1.0,"y":1.0,"z":5.0},"pos":{"x":2.79,"y":3.479,"z":0.0},"rot":{"x":0.0,"y":0.0,"z":0.0,"w":1.0}},{"tableId":0,"type":3,"size":{"x":1.0,"y":1.0,"z":5.0},"pos":{"x":2.79,"y":0.5,"z":0.0},"rot":{"x":0.0,"y":0.0,"z":0.0,"w":1.0}},{"tableId":0,"type":3,"size":{"x":1.0,"y":1.0,"z":5.0},"pos":{"x":-2.79,"y":3.479,"z":0.0},"rot":{"x":0.0,"y":0.0,"z":0.0,"w":1.0}},{"tableId":0,"type":3,"size":{"x":1.0,"y":1.0,"z":5.0},"pos":{"x":-2.79,"y":0.5,"z":0.0},"rot":{"x":0.0,"y":0.0,"z":0.0,"w":1.0}},{"tableId":0,"type":3,"size":{"x":1.0,"y":1.0,"z":5.0},"pos":{"x":2.79,"y":6.49999952,"z":0.0},"rot":{"x":0.0,"y":0.0,"z":0.0,"w":1.0}},{"tableId":0,"type":3,"size":{"x":1.0,"y":1.0,"z":5.0},"pos":{"x":-2.79,"y":6.49999952,"z":0.0},"rot":{"x":0.0,"y":0.0,"z":0.0,"w":1.0}},{"tableId":0,"type":15,"size":{"x":1.0,"y":1.0,"z":1.0},"pos":{"x":2.787,"y":1.5,"z":-1.84775925},"rot":{"x":0.0,"y":0.0,"z":0.0,"w":1.0}},{"tableId":0,"type":15,"size":{"x":1.0,"y":1.0,"z":1.0},"pos":{"x":-2.787,"y":1.5,"z":-1.84775925},"rot":{"x":0.0,"y":0.0,"z":0.0,"w":1.0}},{"tableId":0,"type":15,"size":{"x":1.0,"y":1.0,"z":1.0},"pos":{"x":2.787,"y":4.5,"z":-1.84775925},"rot":{"x":0.0,"y":0.0,"z":0.0,"w":1.0}},{"tableId":0,"type":15,"size":{"x":1.0,"y":1.0,"z":1.0},"pos":{"x":-2.787,"y":4.5,"z":-1.84775925},"rot":{"x":0.0,"y":0.0,"z":0.0,"w":1.0}},{"tableId":0,"type":15,"size":{"x":1.0,"y":1.0,"z":1.0},"pos":{"x":2.787,"y":7.49999952,"z":-1.84775925},"rot":{"x":0.0,"y":0.0,"z":0.0,"w":1.0}},{"tableId":0,"type":15,"size":{"x":1.0,"y":1.0,"z":1.0},"pos":{"x":-2.787,"y":7.49999952,"z":-1.84775925},"rot":{"x":0.0,"y":0.0,"z":0.0,"w":1.0}},{"tableId":0,"type":15,"size":{"x":1.0,"y":1.0,"z":1.0},"pos":{"x":2.787,"y":1.5,"z":-0.871999741},"rot":{"x":0.0,"y":0.0,"z":0.0,"w":1.0}},{"tableId":0,"type":15,"size":{"x":1.0,"y":1.0,"z":1.0},"pos":{"x":-2.787,"y":1.5,"z":-0.871999741},"rot":{"x":0.0,"y":0.0,"z":0.0,"w":1.0}},{"tableId":0,"type":15,"size":{"x":1.0,"y":1.0,"z":1.0},"pos":{"x":2.787,"y":4.5,"z":-0.871999741},"rot":{"x":0.0,"y":0.0,"z":0.0,"w":1.0}},{"tableId":0,"type":15,"size":{"x":1.0,"y":1.0,"z":1.0},"pos":{"x":-2.787,"y":4.5,"z":-0.871999741},"rot":{"x":0.0,"y":0.0,"z":0.0,"w":1.0}},{"tableId":0,"type":15,"size":{"x":1.0,"y":1.0,"z":1.0},"pos":{"x":2.787,"y":7.49999952,"z":-0.871999741},"rot":{"x":0.0,"y":0.0,"z":0.0,"w":1.0}},{"tableId":0,"type":15,"size":{"x":1.0,"y":1.0,"z":1.0},"pos":{"x":-2.787,"y":7.49999952,"z":-0.871999741},"rot":{"x":0.0,"y":0.0,"z":0.0,"w":1.0}},{"tableId":0,"type":15,"size":{"x":1.0,"y":1.0,"z":1.0},"pos":{"x":2.787,"y":1.5,"z":0.125},"rot":{"x":0.0,"y":0.0,"z":0.0,"w":1.0}},{"tableId":0,"type":15,"size":{"x":1.0,"y":1.0,"z":1.0},"pos":{"x":-2.787,"y":1.5,"z":0.125},"rot":{"x":0.0,"y":0.0,"z":0.0,"w":1.0}},{"tableId":0,"type":15,"size":{"x":1.0,"y":1.0,"z":1.0},"pos":{"x":2.787,"y":4.5,"z":0.125},"rot":{"x":0.0,"y":0.0,"z":0.0,"w":1.0}},{"tableId":0,"type":15,"size":{"x":1.0,"y":1.0,"z":1.0},"pos":{"x":-2.787,"y":4.5,"z":0.125},"rot":{"x":0.0,"y":0.0,"z":0.0,"w":1.0}},{"tableId":0,"type":15,"size":{"x":1.0,"y":1.0,"z":1.0},"pos":{"x":2.787,"y":7.49999952,"z":0.125},"rot":{"x":0.0,"y":0.0,"z":0.0,"w":1.0}},{"tableId":0,"type":15,"size":{"x":1.0,"y":1.0,"z":1.0},"pos":{"x":-2.787,"y":7.49999952,"z":0.125},"rot":{"x":0.0,"y":0.0,"z":0.0,"w":1.0}},{"tableId":0,"type":15,"size":{"x":1.0,"y":1.0,"z":1.0},"pos":{"x":2.787,"y":1.5,"z":1.12199974},"rot":{"x":0.0,"y":0.0,"z":0.0,"w":1.0}},{"tableId":0,"type":15,"size":{"x":1.0,"y":1.0,"z":1.0},"pos":{"x":-2.787,"y":1.5,"z":1.12199974},"rot":{"x":0.0,"y":0.0,"z":0.0,"w":1.0}},{"tableId":0,"type":15,"size":{"x":1.0,"y":1.0,"z":1.0},"pos":{"x":2.787,"y":4.5,"z":1.12199974},"rot":{"x":0.0,"y":0.0,"z":0.0,"w":1.0}},{"tableId":0,"type":15,"size":{"x":1.0,"y":1.0,"z":1.0},"pos":{"x":-2.787,"y":4.5,"z":1.12199974},"rot":{"x":0.0,"y":0.0,"z":0.0,"w":1.0}},{"tableId":0,"type":15,"size":{"x":1.0,"y":1.0,"z":1.0},"pos":{"x":2.787,"y":7.49999952,"z":1.12199974},"rot":{"x":0.0,"y":0.0,"z":0.0,"w":1.0}},{"tableId":0,"type":15,"size":{"x":1.0,"y":1.0,"z":1.0},"pos":{"x":-2.787,"y":7.49999952,"z":1.12199974},"rot":{"x":0.0,"y":0.0,"z":0.0,"w":1.0}},{"tableId":0,"type":15,"size":{"x":1.0,"y":1.0,"z":1.0},"pos":{"x":2.787,"y":1.5,"z":2.038},"rot":{"x":0.0,"y":0.0,"z":0.0,"w":1.0}},{"tableId":0,"type":15,"size":{"x":1.0,"y":1.0,"z":1.0},"pos":{"x":-2.787,"y":1.5,"z":2.038},"rot":{"x":0.0,"y":0.0,"z":0.0,"w":1.0}},{"tableId":0,"type":15,"size":{"x":1.0,"y":1.0,"z":1.0},"pos":{"x":2.787,"y":4.5,"z":2.038},"rot":{"x":0.0,"y":0.0,"z":0.0,"w":1.0}},{"tableId":0,"type":15,"size":{"x":1.0,"y":1.0,"z":1.0},"pos":{"x":-2.787,"y":4.5,"z":2.038},"rot":{"x":0.0,"y":0.0,"z":0.0,"w":1.0}},{"tableId":0,"type":15,"size":{"x":1.0,"y":1.0,"z":1.0},"pos":{"x":2.787,"y":7.49999952,"z":2.038},"rot":{"x":0.0,"y":0.0,"z":0.0,"w":1.0}},{"tableId":0,"type":15,"size":{"x":1.0,"y":1.0,"z":1.0},"pos":{"x":-2.787,"y":7.49999952,"z":2.038},"rot":{"x":0.0,"y":0.0,"z":0.0,"w":1.0}},{"tableId":0,"type":1,"size":{"x":1.0,"y":2.0,"z":1.0},"pos":{"x":1.802,"y":4.0,"z":0.0},"rot":{"x":0.0,"y":0.7071068,"z":0.0,"w":0.7071068}},{"tableId":0,"type":1,"size":{"x":1.0,"y":2.0,"z":1.0},"pos":{"x":1.802,"y":1.0,"z":0.0},"rot":{"x":0.0,"y":0.7071068,"z":0.0,"w":0.7071068}},{"tableId":0,"type":1,"size":{"x":1.0,"y":2.0,"z":1.0},"pos":{"x":-1.802,"y":4.0,"z":0.0},"rot":{"x":0.0,"y":0.7071068,"z":0.0,"w":0.7071068}},{"tableId":0,"type":1,"size":{"x":1.0,"y":2.0,"z":1.0},"pos":{"x":-1.802,"y":1.0,"z":0.0},"rot":{"x":0.0,"y":0.7071068,"z":0.0,"w":0.7071068}},{"tableId":0,"type":1,"size":{"x":1.0,"y":2.0,"z":1.0},"pos":{"x":1.802,"y":6.99999952,"z":0.0},"rot":{"x":0.0,"y":0.7071068,"z":0.0,"w":0.7071068}},{"tableId":0,"type":1,"size":{"x":1.0,"y":2.0,"z":1.0},"pos":{"x":-1.802,"y":6.99999952,"z":0.0},"rot":{"x":0.0,"y":0.7071068,"z":0.0,"w":0.7071068}},{"tableId":0,"type":1,"size":{"x":1.0,"y":2.0,"z":1.0},"pos":{"x":0.0,"y":4.0,"z":2.0},"rot":{"x":0.0,"y":0.0,"z":0.0,"w":1.0}},{"tableId":0,"type":3,"size":{"x":1.0,"y":1.0,"z":3.0},"pos":{"x":2.0,"y":2.49999952,"z":0.0},"rot":{"x":0.0,"y":0.0,"z":0.0,"w":1.0}},{"tableId":0,"type":3,"size":{"x":1.0,"y":1.0,"z":3.0},"pos":{"x":-2.0,"y":2.49999952,"z":0.0},"rot":{"x":0.0,"y":0.0,"z":0.0,"w":1.0}},{"tableId":0,"type":3,"size":{"x":3.0,"y":1.0,"z":1.0},"pos":{"x":0.0,"y":2.49999952,"z":-2.0},"rot":{"x":0.0,"y":0.0,"z":0.0,"w":1.0}},{"tableId":0,"type":3,"size":{"x":3.0,"y":1.0,"z":1.0},"pos":{"x":0.0,"y":2.49999952,"z":2.0},"rot":{"x":0.0,"y":0.0,"z":0.0,"w":1.0}},{"tableId":0,"type":3,"size":{"x":1.0,"y":1.0,"z":3.0},"pos":{"x":2.0,"y":5.49999952,"z":0.0},"rot":{"x":0.0,"y":0.0,"z":0.0,"w":1.0}},{"tableId":0,"type":3,"size":{"x":1.0,"y":1.0,"z":3.0},"pos":{"x":-2.0,"y":5.49999952,"z":0.0},"rot":{"x":0.0,"y":0.0,"z":0.0,"w":1.0}},{"tableId":0,"type":3,"size":{"x":3.0,"y":1.0,"z":1.0},"pos":{"x":0.0,"y":5.49999952,"z":-2.0},"rot":{"x":0.0,"y":0.0,"z":0.0,"w":1.0}},{"tableId":0,"type":3,"size":{"x":3.0,"y":1.0,"z":1.0},"pos":{"x":0.0,"y":8.5,"z":-1.8499999},"rot":{"x":0.0,"y":0.0,"z":0.0,"w":1.0}},{"tableId":0,"type":3,"size":{"x":3.0,"y":1.0,"z":1.0},"pos":{"x":0.0,"y":8.5,"z":1.8499999},"rot":{"x":0.0,"y":0.0,"z":0.0,"w":1.0}},{"tableId":0,"type":3,"size":{"x":3.0,"y":1.0,"z":1.0},"pos":{"x":0.0,"y":5.49999952,"z":2.0},"rot":{"x":0.0,"y":0.0,"z":0.0,"w":1.0}},{"tableId":0,"type":3,"size":{"x":1.0,"y":1.0,"z":2.0},"pos":{"x":1.6,"y":8.5,"z":0.0},"rot":{"x":0.0,"y":0.0,"z":0.0,"w":1.0}},{"tableId":0,"type":3,"size":{"x":1.0,"y":1.0,"z":2.0},"pos":{"x":-1.6,"y":8.5,"z":0.0},"rot":{"x":0.0,"y":0.0,"z":0.0,"w":1.0}},{"tableId":0,"type":1,"size":{"x":1.0,"y":1.0,"z":1.0},"pos":{"x":1.6,"y":9.5,"z":0.0},"rot":{"x":0.0,"y":0.0,"z":0.0,"w":1.0}},{"tableId":0,"type":1,"size":{"x":1.0,"y":1.0,"z":1.0},"pos":{"x":0.0,"y":9.5,"z":1.82999992},"rot":{"x":0.0,"y":0.0,"z":0.0,"w":1.0}},{"tableId":0,"type":1,"size":{"x":1.0,"y":1.0,"z":1.0},"pos":{"x":0.0,"y":9.5,"z":-1.5999999},"rot":{"x":0.0,"y":0.0,"z":0.0,"w":1.0}},{"tableId":0,"type":1,"size":{"x":1.0,"y":1.0,"z":1.0},"pos":{"x":-1.6,"y":9.5,"z":0.0},"rot":{"x":0.0,"y":0.0,"z":0.0,"w":1.0}},{"tableId":0,"type":14,"size":{"x":1.0,"y":3.0,"z":1.0},"pos":{"x":-0.5,"y":7.49999952,"z":-0.5},"rot":{"x":0.0,"y":0.0,"z":0.0,"w":1.0}},{"tableId":0,"type":14,"size":{"x":1.0,"y":3.0,"z":1.0},"pos":{"x":0.5,"y":7.49999952,"z":0.5},"rot":{"x":0.0,"y":0.0,"z":0.0,"w":1.0}},{"tableId":0,"type":14,"size":{"x":1.0,"y":1.0,"z":1.0},"pos":{"x":-0.5,"y":9.5,"z":0.5},"rot":{"x":0.0,"y":0.0,"z":0.0,"w":1.0}},{"tableId":0,"type":14,"size":{"x":1.0,"y":1.0,"z":1.0},"pos":{"x":-0.5,"y":9.5,"z":-0.5},"rot":{"x":0.0,"y":0.0,"z":0.0,"w":1.0}},{"tableId":0,"type":14,"size":{"x":1.0,"y":3.0,"z":1.0},"pos":{"x":0.5,"y":4.5,"z":0.5},"rot":{"x":0.0,"y":0.0,"z":0.0,"w":1.0}},{"tableId":0,"type":14,"size":{"x":1.0,"y":1.0,"z":1.0},"pos":{"x":0.5,"y":9.5,"z":0.5},"rot":{"x":0.0,"y":0.0,"z":0.0,"w":1.0}},{"tableId":0,"type":14,"size":{"x":1.0,"y":3.0,"z":1.0},"pos":{"x":-0.5,"y":4.5,"z":-0.5},"rot":{"x":0.0,"y":0.0,"z":0.0,"w":1.0}},{"tableId":0,"type":14,"size":{"x":1.0,"y":3.0,"z":1.0},"pos":{"x":0.5,"y":4.5,"z":-0.5},"rot":{"x":0.0,"y":0.0,"z":0.0,"w":1.0}},{"tableId":0,"type":14,"size":{"x":1.0,"y":3.0,"z":1.0},"pos":{"x":0.5,"y":7.49999952,"z":-0.5},"rot":{"x":0.0,"y":0.0,"z":0.0,"w":1.0}},{"tableId":0,"type":14,"size":{"x":1.0,"y":1.0,"z":1.0},"pos":{"x":0.5,"y":9.5,"z":-0.5},"rot":{"x":0.0,"y":0.0,"z":0.0,"w":1.0}},{"tableId":0,"type":14,"size":{"x":1.0,"y":3.0,"z":1.0},"pos":{"x":-0.5,"y":4.5,"z":0.5},"rot":{"x":0.0,"y":0.0,"z":0.0,"w":1.0}},{"tableId":0,"type":14,"size":{"x":1.0,"y":3.0,"z":1.0},"pos":{"x":-0.5,"y":7.49999952,"z":0.5},"rot":{"x":0.0,"y":0.0,"z":0.0,"w":1.0}},{"tableId":0,"type":14,"size":{"x":1.0,"y":3.0,"z":1.0},"pos":{"x":-0.5,"y":1.5,"z":0.5},"rot":{"x":0.0,"y":0.0,"z":0.0,"w":1.0}},{"tableId":0,"type":14,"size":{"x":1.0,"y":3.0,"z":1.0},"pos":{"x":0.5,"y":1.5,"z":-0.5},"rot":{"x":0.0,"y":0.0,"z":0.0,"w":1.0}},{"tableId":0,"type":14,"size":{"x":1.0,"y":3.0,"z":1.0},"pos":{"x":0.5,"y":1.5,"z":0.5},"rot":{"x":0.0,"y":0.0,"z":0.0,"w":1.0}},{"tableId":0,"type":14,"size":{"x":1.0,"y":3.0,"z":1.0},"pos":{"x":-0.5,"y":1.5,"z":-0.5},"rot":{"x":0.0,"y":0.0,"z":0.0,"w":1.0}}],"tables":[{"id":0,"pos":{"x":0.0,"y":2.9,"z":5.0},"rot":{"x":0.0,"y":0.0,"z":0.0,"w":1.0},"scl":{"x":1.0,"y":1.0,"z":1.0},"dim":{"x":9.8,"y":5.0,"z":0.0},"doRot":false,"rotSpd":0.0,"movH":false,"movHMin":0.0,"movHMax":0.0,"dirH":0,"movSpdH":0.0,"movV":false,"movVMin":0.0,"movVMax":0.0,"dirV":0,"movSpdV":0.0}],"blockers":[]}]}