{"levelIndex":654,"moveCount":26,"difficulty":1,"stages":[{"objects":[{"tableId":0,"type":41,"size":{"x":1.0,"y":2.0,"z":1.0},"pos":{"x":-3.07000017,"y":1.0,"z":0.5},"rot":{"x":0.0,"y":0.0,"z":0.0,"w":1.0}},{"tableId":0,"type":41,"size":{"x":1.0,"y":2.0,"z":1.0},"pos":{"x":-3.07000017,"y":4.0,"z":0.5},"rot":{"x":0.0,"y":0.0,"z":0.0,"w":1.0}},{"tableId":0,"type":41,"size":{"x":1.0,"y":2.0,"z":1.0},"pos":{"x":-0.07000017,"y":1.0,"z":0.5},"rot":{"x":0.0,"y":0.0,"z":0.0,"w":1.0}},{"tableId":0,"type":41,"size":{"x":1.0,"y":2.0,"z":1.0},"pos":{"x":-0.07000017,"y":4.0,"z":0.5},"rot":{"x":0.0,"y":0.0,"z":0.0,"w":1.0}},{"tableId":0,"type":41,"size":{"x":1.0,"y":2.0,"z":1.0},"pos":{"x":2.92999983,"y":1.0,"z":0.5},"rot":{"x":0.0,"y":0.0,"z":0.0,"w":1.0}},{"tableId":0,"type":41,"size":{"x":1.0,"y":2.0,"z":1.0},"pos":{"x":2.92999983,"y":4.0,"z":0.5},"rot":{"x":0.0,"y":0.0,"z":0.0,"w":1.0}},{"tableId":0,"type":41,"size":{"x":3.0,"y":1.0,"z":1.0},"pos":{"x":-1.57000017,"y":5.49999952,"z":0.5},"rot":{"x":0.0,"y":0.0,"z":0.0,"w":1.0}},{"tableId":0,"type":41,"size":{"x":3.0,"y":1.0,"z":1.0},"pos":{"x":1.42999983,"y":5.49999952,"z":0.5},"rot":{"x":0.0,"y":0.0,"z":0.0,"w":1.0}},{"tableId":0,"type":41,"size":{"x":4.0,"y":1.0,"z":1.0},"pos":{"x":-0.07000017,"y":7.49999952,"z":0.5},"rot":{"x":0.0,"y":0.0,"z":0.0,"w":1.0}},{"tableId":0,"type":41,"size":{"x":3.0,"y":1.0,"z":1.0},"pos":{"x":-0.07000017,"y":9.5,"z":0.5},"rot":{"x":0.0,"y":0.0,"z":0.0,"w":1.0}},{"tableId":0,"type":11,"size":{"x":1.0,"y":1.0,"z":1.0},"pos":{"x":-3.07000017,"y":3.5,"z":-1.5},"rot":{"x":0.0,"y":0.0,"z":0.0,"w":1.0}},{"tableId":0,"type":11,"size":{"x":1.0,"y":1.0,"z":1.0},"pos":{"x":-3.07000017,"y":0.5,"z":-1.5},"rot":{"x":0.0,"y":0.0,"z":0.0,"w":1.0}},{"tableId":0,"type":11,"size":{"x":1.0,"y":1.0,"z":1.0},"pos":{"x":2.92999983,"y":3.5,"z":-1.5},"rot":{"x":0.0,"y":0.0,"z":0.0,"w":1.0}},{"tableId":0,"type":11,"size":{"x":1.0,"y":1.0,"z":1.0},"pos":{"x":2.92999983,"y":0.5,"z":-1.5},"rot":{"x":0.0,"y":0.0,"z":0.0,"w":1.0}},{"tableId":0,"type":11,"size":{"x":1.0,"y":1.0,"z":1.0},"pos":{"x":-3.07000017,"y":1.5,"z":-1.5},"rot":{"x":0.0,"y":0.0,"z":0.0,"w":1.0}},{"tableId":0,"type":11,"size":{"x":1.0,"y":1.0,"z":1.0},"pos":{"x":2.92999983,"y":1.5,"z":-1.5},"rot":{"x":0.0,"y":0.0,"z":0.0,"w":1.0}},{"tableId":0,"type":21,"size":{"x":1.0,"y":2.0,"z":1.0},"pos":{"x":-4.07,"y":1.0,"z":-1.5},"rot":{"x":0.0,"y":0.0,"z":0.0,"w":1.0}},{"tableId":0,"type":21,"size":{"x":1.0,"y":2.0,"z":1.0},"pos":{"x":-2.07000017,"y":1.0,"z":-1.5},"rot":{"x":0.0,"y":0.0,"z":0.0,"w":1.0}},{"tableId":0,"type":21,"size":{"x":1.0,"y":2.0,"z":1.0},"pos":{"x":-4.07,"y":1.0,"z":-0.5},"rot":{"x":0.0,"y":0.0,"z":0.0,"w":1.0}},{"tableId":0,"type":21,"size":{"x":1.0,"y":2.0,"z":1.0},"pos":{"x":-2.07000017,"y":1.0,"z":-0.5},"rot":{"x":0.0,"y":0.0,"z":0.0,"w":1.0}},{"tableId":0,"type":21,"size":{"x":1.0,"y":2.0,"z":1.0},"pos":{"x":1.92999983,"y":1.0,"z":-0.5},"rot":{"x":0.0,"y":0.0,"z":0.0,"w":1.0}},{"tableId":0,"type":21,"size":{"x":1.0,"y":2.0,"z":1.0},"pos":{"x":3.92999983,"y":1.0,"z":-0.5},"rot":{"x":0.0,"y":0.0,"z":0.0,"w":1.0}},{"tableId":0,"type":21,"size":{"x":1.0,"y":2.0,"z":1.0},"pos":{"x":1.92999983,"y":1.0,"z":-1.5},"rot":{"x":0.0,"y":0.0,"z":0.0,"w":1.0}},{"tableId":0,"type":21,"size":{"x":1.0,"y":2.0,"z":1.0},"pos":{"x":3.92999983,"y":1.0,"z":-1.5},"rot":{"x":0.0,"y":0.0,"z":0.0,"w":1.0}},{"tableId":0,"type":21,"size":{"x":3.0,"y":1.0,"z":1.0},"pos":{"x":-3.07000017,"y":2.5,"z":-1.5},"rot":{"x":0.0,"y":0.0,"z":0.0,"w":1.0}},{"tableId":0,"type":21,"size":{"x":3.0,"y":1.0,"z":1.0},"pos":{"x":-3.07000017,"y":4.5,"z":-1.5},"rot":{"x":0.0,"y":0.0,"z":0.0,"w":1.0}},{"tableId":0,"type":21,"size":{"x":3.0,"y":1.0,"z":1.0},"pos":{"x":-3.07000017,"y":2.5,"z":-0.5},"rot":{"x":0.0,"y":0.0,"z":0.0,"w":1.0}},{"tableId":0,"type":21,"size":{"x":3.0,"y":1.0,"z":1.0},"pos":{"x":-3.07000017,"y":4.5,"z":-0.5},"rot":{"x":0.0,"y":0.0,"z":0.0,"w":1.0}},{"tableId":0,"type":21,"size":{"x":3.0,"y":1.0,"z":1.0},"pos":{"x":2.92999983,"y":2.5,"z":-0.5},"rot":{"x":0.0,"y":0.0,"z":0.0,"w":1.0}},{"tableId":0,"type":21,"size":{"x":3.0,"y":1.0,"z":1.0},"pos":{"x":2.92999983,"y":4.5,"z":-0.5},"rot":{"x":0.0,"y":0.0,"z":0.0,"w":1.0}},{"tableId":0,"type":21,"size":{"x":3.0,"y":1.0,"z":1.0},"pos":{"x":2.92999983,"y":2.5,"z":-1.5},"rot":{"x":0.0,"y":0.0,"z":0.0,"w":1.0}},{"tableId":0,"type":21,"size":{"x":3.0,"y":1.0,"z":1.0},"pos":{"x":2.92999983,"y":4.5,"z":-1.5},"rot":{"x":0.0,"y":0.0,"z":0.0,"w":1.0}},{"tableId":0,"type":3,"size":{"x":1.0,"y":2.0,"z":1.0},"pos":{"x":0.9299998,"y":1.0,"z":-1.5},"rot":{"x":0.0,"y":0.0,"z":0.0,"w":1.0}},{"tableId":0,"type":3,"size":{"x":1.0,"y":2.0,"z":1.0},"pos":{"x":0.9299998,"y":4.0,"z":-1.5},"rot":{"x":0.0,"y":0.0,"z":0.0,"w":1.0}},{"tableId":0,"type":3,"size":{"x":1.0,"y":2.0,"z":1.0},"pos":{"x":0.9299998,"y":1.0,"z":-0.5},"rot":{"x":0.0,"y":0.0,"z":0.0,"w":1.0}},{"tableId":0,"type":3,"size":{"x":1.0,"y":2.0,"z":1.0},"pos":{"x":0.9299998,"y":4.0,"z":-0.5},"rot":{"x":0.0,"y":0.0,"z":0.0,"w":1.0}},{"tableId":0,"type":3,"size":{"x":1.0,"y":2.0,"z":1.0},"pos":{"x":-1.07000017,"y":4.0,"z":-1.5},"rot":{"x":0.0,"y":0.0,"z":0.0,"w":1.0}},{"tableId":0,"type":3,"size":{"x":1.0,"y":2.0,"z":1.0},"pos":{"x":-1.07000017,"y":4.0,"z":-0.5},"rot":{"x":0.0,"y":0.0,"z":0.0,"w":1.0}},{"tableId":0,"type":3,"size":{"x":1.0,"y":2.0,"z":1.0},"pos":{"x":-1.07000017,"y":1.0,"z":-1.5},"rot":{"x":0.0,"y":0.0,"z":0.0,"w":1.0}},{"tableId":0,"type":3,"size":{"x":1.0,"y":2.0,"z":1.0},"pos":{"x":-1.07000017,"y":1.0,"z":-0.5},"rot":{"x":0.0,"y":0.0,"z":0.0,"w":1.0}},{"tableId":0,"type":3,"size":{"x":1.0,"y":2.0,"z":1.0},"pos":{"x":-0.07000017,"y":4.0,"z":-1.5},"rot":{"x":0.0,"y":0.0,"z":0.0,"w":1.0}},{"tableId":0,"type":3,"size":{"x":1.0,"y":2.0,"z":1.0},"pos":{"x":-0.07000017,"y":4.0,"z":-0.5},"rot":{"x":0.0,"y":0.0,"z":0.0,"w":1.0}},{"tableId":0,"type":3,"size":{"x":1.0,"y":2.0,"z":1.0},"pos":{"x":-0.07000017,"y":1.0,"z":-1.5},"rot":{"x":0.0,"y":0.0,"z":0.0,"w":1.0}},{"tableId":0,"type":3,"size":{"x":1.0,"y":2.0,"z":1.0},"pos":{"x":-0.07000017,"y":1.0,"z":-0.5},"rot":{"x":0.0,"y":0.0,"z":0.0,"w":1.0}},{"tableId":0,"type":13,"size":{"x":1.0,"y":1.0,"z":1.0},"pos":{"x":-4.07,"y":3.5,"z":-1.5},"rot":{"x":0.0,"y":0.0,"z":0.0,"w":1.0}},{"tableId":0,"type":13,"size":{"x":1.0,"y":1.0,"z":1.0},"pos":{"x":-4.07,"y":3.5,"z":-0.5},"rot":{"x":0.0,"y":0.0,"z":0.0,"w":1.0}},{"tableId":0,"type":13,"size":{"x":1.0,"y":1.0,"z":1.0},"pos":{"x":-2.07000017,"y":3.5,"z":-1.5},"rot":{"x":0.0,"y":0.0,"z":0.0,"w":1.0}},{"tableId":0,"type":13,"size":{"x":1.0,"y":1.0,"z":1.0},"pos":{"x":1.92999983,"y":3.5,"z":-1.5},"rot":{"x":0.0,"y":0.0,"z":0.0,"w":1.0}},{"tableId":0,"type":13,"size":{"x":1.0,"y":1.0,"z":1.0},"pos":{"x":3.92999983,"y":3.5,"z":-1.5},"rot":{"x":0.0,"y":0.0,"z":0.0,"w":1.0}},{"tableId":0,"type":13,"size":{"x":1.0,"y":1.0,"z":1.0},"pos":{"x":3.92999983,"y":3.5,"z":-0.5},"rot":{"x":0.0,"y":0.0,"z":0.0,"w":1.0}},{"tableId":0,"type":13,"size":{"x":1.0,"y":1.0,"z":1.0},"pos":{"x":1.92999983,"y":3.5,"z":-0.5},"rot":{"x":0.0,"y":0.0,"z":0.0,"w":1.0}},{"tableId":0,"type":13,"size":{"x":1.0,"y":1.0,"z":1.0},"pos":{"x":-2.07000017,"y":3.5,"z":-0.5},"rot":{"x":0.0,"y":0.0,"z":0.0,"w":1.0}},{"tableId":0,"type":13,"size":{"x":1.0,"y":1.0,"z":1.0},"pos":{"x":-3.07000017,"y":5.49999952,"z":-1.5},"rot":{"x":0.0,"y":0.0,"z":0.0,"w":1.0}},{"tableId":0,"type":13,"size":{"x":1.0,"y":1.0,"z":1.0},"pos":{"x":-3.07000017,"y":5.49999952,"z":-0.5},"rot":{"x":0.0,"y":0.0,"z":0.0,"w":1.0}},{"tableId":0,"type":13,"size":{"x":1.0,"y":1.0,"z":1.0},"pos":{"x":3.07,"y":5.49999952,"z":-1.5},"rot":{"x":0.0,"y":0.0,"z":0.0,"w":1.0}},{"tableId":0,"type":13,"size":{"x":1.0,"y":1.0,"z":1.0},"pos":{"x":3.07,"y":5.49999952,"z":-0.5},"rot":{"x":0.0,"y":0.0,"z":0.0,"w":1.0}},{"tableId":0,"type":14,"size":{"x":1.0,"y":1.0,"z":1.0},"pos":{"x":-0.07000017,"y":2.5,"z":-0.5},"rot":{"x":0.0,"y":0.0,"z":0.0,"w":1.0}},{"tableId":0,"type":14,"size":{"x":1.0,"y":1.0,"z":1.0},"pos":{"x":0.9299998,"y":2.5,"z":-0.5},"rot":{"x":0.0,"y":0.0,"z":0.0,"w":1.0}},{"tableId":0,"type":14,"size":{"x":1.0,"y":1.0,"z":1.0},"pos":{"x":-1.07000017,"y":2.5,"z":-0.5},"rot":{"x":0.0,"y":0.0,"z":0.0,"w":1.0}},{"tableId":0,"type":14,"size":{"x":1.0,"y":1.0,"z":1.0},"pos":{"x":-1.07000017,"y":2.5,"z":-1.5},"rot":{"x":0.0,"y":0.0,"z":0.0,"w":1.0}},{"tableId":0,"type":14,"size":{"x":1.0,"y":1.0,"z":1.0},"pos":{"x":-0.07000017,"y":2.5,"z":-1.5},"rot":{"x":0.0,"y":0.0,"z":0.0,"w":1.0}},{"tableId":0,"type":14,"size":{"x":1.0,"y":1.0,"z":1.0},"pos":{"x":0.9299998,"y":2.5,"z":-1.5},"rot":{"x":0.0,"y":0.0,"z":0.0,"w":1.0}},{"tableId":0,"type":14,"size":{"x":1.0,"y":1.0,"z":1.0},"pos":{"x":-1.07000017,"y":5.49999952,"z":-1.5},"rot":{"x":0.0,"y":0.0,"z":0.0,"w":1.0}},{"tableId":0,"type":14,"size":{"x":1.0,"y":1.0,"z":1.0},"pos":{"x":-1.07000017,"y":5.49999952,"z":-0.5},"rot":{"x":0.0,"y":0.0,"z":0.0,"w":1.0}},{"tableId":0,"type":14,"size":{"x":1.0,"y":1.0,"z":1.0},"pos":{"x":-0.07000017,"y":5.49999952,"z":-0.5},"rot":{"x":0.0,"y":0.0,"z":0.0,"w":1.0}},{"tableId":0,"type":14,"size":{"x":1.0,"y":1.0,"z":1.0},"pos":{"x":-0.07000017,"y":5.49999952,"z":-1.5},"rot":{"x":0.0,"y":0.0,"z":0.0,"w":1.0}},{"tableId":0,"type":14,"size":{"x":1.0,"y":1.0,"z":1.0},"pos":{"x":0.9299998,"y":5.49999952,"z":-1.5},"rot":{"x":0.0,"y":0.0,"z":0.0,"w":1.0}},{"tableId":0,"type":14,"size":{"x":1.0,"y":1.0,"z":1.0},"pos":{"x":0.9299998,"y":5.49999952,"z":-0.5},"rot":{"x":0.0,"y":0.0,"z":0.0,"w":1.0}},{"tableId":0,"type":11,"size":{"x":1.0,"y":1.0,"z":1.0},"pos":{"x":-3.07000017,"y":2.5,"z":0.5},"rot":{"x":0.0,"y":0.0,"z":0.0,"w":1.0}},{"tableId":0,"type":11,"size":{"x":1.0,"y":1.0,"z":1.0},"pos":{"x":-0.07000017,"y":2.5,"z":0.5},"rot":{"x":0.0,"y":0.0,"z":0.0,"w":1.0}},{"tableId":0,"type":11,"size":{"x":1.0,"y":1.0,"z":1.0},"pos":{"x":2.92999983,"y":2.5,"z":0.5},"rot":{"x":0.0,"y":0.0,"z":0.0,"w":1.0}},{"tableId":0,"type":11,"size":{"x":1.0,"y":1.0,"z":1.0},"pos":{"x":1.42999983,"y":6.49999952,"z":0.5},"rot":{"x":0.0,"y":0.0,"z":0.0,"w":1.0}},{"tableId":0,"type":11,"size":{"x":1.0,"y":1.0,"z":1.0},"pos":{"x":-1.57000017,"y":6.49999952,"z":0.5},"rot":{"x":0.0,"y":0.0,"z":0.0,"w":1.0}},{"tableId":0,"type":11,"size":{"x":1.0,"y":1.0,"z":1.0},"pos":{"x":-1.07000017,"y":8.5,"z":0.5},"rot":{"x":0.0,"y":0.0,"z":0.0,"w":1.0}},{"tableId":0,"type":11,"size":{"x":1.0,"y":1.0,"z":1.0},"pos":{"x":0.9299998,"y":8.5,"z":0.5},"rot":{"x":0.0,"y":0.0,"z":0.0,"w":1.0}},{"tableId":0,"type":11,"size":{"x":1.0,"y":1.0,"z":1.0},"pos":{"x":-0.5700002,"y":6.49999952,"z":0.5},"rot":{"x":0.0,"y":0.0,"z":0.0,"w":1.0}},{"tableId":0,"type":11,"size":{"x":1.0,"y":1.0,"z":1.0},"pos":{"x":0.429999828,"y":6.49999952,"z":0.5},"rot":{"x":0.0,"y":0.0,"z":0.0,"w":1.0}},{"tableId":0,"type":11,"size":{"x":1.0,"y":1.0,"z":1.0},"pos":{"x":-0.07000017,"y":8.5,"z":0.5},"rot":{"x":0.0,"y":0.0,"z":0.0,"w":1.0}},{"tableId":0,"type":13,"size":{"x":1.0,"y":1.0,"z":1.0},"pos":{"x":-2.07000017,"y":5.49999952,"z":-1.5},"rot":{"x":0.0,"y":0.0,"z":0.0,"w":1.0}},{"tableId":0,"type":13,"size":{"x":1.0,"y":1.0,"z":1.0},"pos":{"x":-2.07000017,"y":5.49999952,"z":-0.5},"rot":{"x":0.0,"y":0.0,"z":0.0,"w":1.0}},{"tableId":0,"type":13,"size":{"x":1.0,"y":1.0,"z":1.0},"pos":{"x":-4.07,"y":5.49999952,"z":-1.5},"rot":{"x":0.0,"y":0.0,"z":0.0,"w":1.0}},{"tableId":0,"type":13,"size":{"x":1.0,"y":1.0,"z":1.0},"pos":{"x":-4.07,"y":5.49999952,"z":-0.5},"rot":{"x":0.0,"y":0.0,"z":0.0,"w":1.0}},{"tableId":0,"type":13,"size":{"x":1.0,"y":1.0,"z":1.0},"pos":{"x":4.07,"y":5.49999952,"z":-1.5},"rot":{"x":0.0,"y":0.0,"z":0.0,"w":1.0}},{"tableId":0,"type":13,"size":{"x":1.0,"y":1.0,"z":1.0},"pos":{"x":4.07,"y":5.49999952,"z":-0.5},"rot":{"x":0.0,"y":0.0,"z":0.0,"w":1.0}},{"tableId":0,"type":13,"size":{"x":1.0,"y":1.0,"z":1.0},"pos":{"x":2.07,"y":5.49999952,"z":-1.5},"rot":{"x":0.0,"y":0.0,"z":0.0,"w":1.0}},{"tableId":0,"type":13,"size":{"x":1.0,"y":1.0,"z":1.0},"pos":{"x":2.07,"y":5.49999952,"z":-0.5},"rot":{"x":0.0,"y":0.0,"z":0.0,"w":1.0}},{"tableId":0,"type":41,"size":{"x":1.0,"y":2.0,"z":1.0},"pos":{"x":-3.07000017,"y":1.0,"z":1.5},"rot":{"x":0.0,"y":0.0,"z":0.0,"w":1.0}},{"tableId":0,"type":41,"size":{"x":1.0,"y":2.0,"z":1.0},"pos":{"x":-3.07000017,"y":4.0,"z":1.5},"rot":{"x":0.0,"y":0.0,"z":0.0,"w":1.0}},{"tableId":0,"type":41,"size":{"x":1.0,"y":2.0,"z":1.0},"pos":{"x":-0.07000017,"y":1.0,"z":1.5},"rot":{"x":0.0,"y":0.0,"z":0.0,"w":1.0}},{"tableId":0,"type":41,"size":{"x":1.0,"y":2.0,"z":1.0},"pos":{"x":-0.07000017,"y":4.0,"z":1.5},"rot":{"x":0.0,"y":0.0,"z":0.0,"w":1.0}},{"tableId":0,"type":41,"size":{"x":1.0,"y":2.0,"z":1.0},"pos":{"x":2.92999983,"y":1.0,"z":1.5},"rot":{"x":0.0,"y":0.0,"z":0.0,"w":1.0}},{"tableId":0,"type":41,"size":{"x":1.0,"y":2.0,"z":1.0},"pos":{"x":2.92999983,"y":4.0,"z":1.5},"rot":{"x":0.0,"y":0.0,"z":0.0,"w":1.0}},{"tableId":0,"type":41,"size":{"x":3.0,"y":1.0,"z":1.0},"pos":{"x":-1.57000017,"y":5.49999952,"z":1.5},"rot":{"x":0.0,"y":0.0,"z":0.0,"w":1.0}},{"tableId":0,"type":41,"size":{"x":3.0,"y":1.0,"z":1.0},"pos":{"x":1.42999983,"y":5.49999952,"z":1.5},"rot":{"x":0.0,"y":0.0,"z":0.0,"w":1.0}},{"tableId":0,"type":41,"size":{"x":4.0,"y":1.0,"z":1.0},"pos":{"x":-0.07000017,"y":7.49999952,"z":1.5},"rot":{"x":0.0,"y":0.0,"z":0.0,"w":1.0}},{"tableId":0,"type":41,"size":{"x":3.0,"y":1.0,"z":1.0},"pos":{"x":-0.07000017,"y":9.5,"z":1.5},"rot":{"x":0.0,"y":0.0,"z":0.0,"w":1.0}},{"tableId":0,"type":11,"size":{"x":1.0,"y":1.0,"z":1.0},"pos":{"x":-3.07000017,"y":2.5,"z":1.5},"rot":{"x":0.0,"y":0.0,"z":0.0,"w":1.0}},{"tableId":0,"type":11,"size":{"x":1.0,"y":1.0,"z":1.0},"pos":{"x":-0.07000017,"y":2.5,"z":1.5},"rot":{"x":0.0,"y":0.0,"z":0.0,"w":1.0}},{"tableId":0,"type":11,"size":{"x":1.0,"y":1.0,"z":1.0},"pos":{"x":2.92999983,"y":2.5,"z":1.5},"rot":{"x":0.0,"y":0.0,"z":0.0,"w":1.0}},{"tableId":0,"type":11,"size":{"x":1.0,"y":1.0,"z":1.0},"pos":{"x":1.42999983,"y":6.49999952,"z":1.5},"rot":{"x":0.0,"y":0.0,"z":0.0,"w":1.0}},{"tableId":0,"type":11,"size":{"x":1.0,"y":1.0,"z":1.0},"pos":{"x":-1.57000017,"y":6.49999952,"z":1.5},"rot":{"x":0.0,"y":0.0,"z":0.0,"w":1.0}},{"tableId":0,"type":11,"size":{"x":1.0,"y":1.0,"z":1.0},"pos":{"x":-1.07000017,"y":8.5,"z":1.5},"rot":{"x":0.0,"y":0.0,"z":0.0,"w":1.0}},{"tableId":0,"type":11,"size":{"x":1.0,"y":1.0,"z":1.0},"pos":{"x":0.9299998,"y":8.5,"z":1.5},"rot":{"x":0.0,"y":0.0,"z":0.0,"w":1.0}},{"tableId":0,"type":11,"size":{"x":1.0,"y":1.0,"z":1.0},"pos":{"x":-0.5700002,"y":6.49999952,"z":1.5},"rot":{"x":0.0,"y":0.0,"z":0.0,"w":1.0}},{"tableId":0,"type":11,"size":{"x":1.0,"y":1.0,"z":1.0},"pos":{"x":0.429999828,"y":6.49999952,"z":1.5},"rot":{"x":0.0,"y":0.0,"z":0.0,"w":1.0}},{"tableId":0,"type":11,"size":{"x":1.0,"y":1.0,"z":1.0},"pos":{"x":-0.07000017,"y":8.5,"z":1.5},"rot":{"x":0.0,"y":0.0,"z":0.0,"w":1.0}},{"tableId":0,"type":11,"size":{"x":1.0,"y":1.0,"z":1.0},"pos":{"x":-2.07000017,"y":0.5,"z":0.5},"rot":{"x":0.0,"y":0.0,"z":0.0,"w":1.0}},{"tableId":0,"type":11,"size":{"x":1.0,"y":1.0,"z":1.0},"pos":{"x":-2.07000017,"y":0.5,"z":1.5},"rot":{"x":0.0,"y":0.0,"z":0.0,"w":1.0}},{"tableId":0,"type":11,"size":{"x":1.0,"y":1.0,"z":1.0},"pos":{"x":-1.07000017,"y":0.5,"z":0.5},"rot":{"x":0.0,"y":0.0,"z":0.0,"w":1.0}},{"tableId":0,"type":11,"size":{"x":1.0,"y":1.0,"z":1.0},"pos":{"x":-1.07000017,"y":0.5,"z":1.5},"rot":{"x":0.0,"y":0.0,"z":0.0,"w":1.0}},{"tableId":0,"type":11,"size":{"x":1.0,"y":1.0,"z":1.0},"pos":{"x":-1.07000017,"y":1.5,"z":0.5},"rot":{"x":0.0,"y":0.0,"z":0.0,"w":1.0}},{"tableId":0,"type":11,"size":{"x":1.0,"y":1.0,"z":1.0},"pos":{"x":-1.07000017,"y":1.5,"z":1.5},"rot":{"x":0.0,"y":0.0,"z":0.0,"w":1.0}},{"tableId":0,"type":11,"size":{"x":1.0,"y":1.0,"z":1.0},"pos":{"x":-2.07000017,"y":1.5,"z":0.5},"rot":{"x":0.0,"y":0.0,"z":0.0,"w":1.0}},{"tableId":0,"type":11,"size":{"x":1.0,"y":1.0,"z":1.0},"pos":{"x":-2.07000017,"y":1.5,"z":1.5},"rot":{"x":0.0,"y":0.0,"z":0.0,"w":1.0}},{"tableId":0,"type":11,"size":{"x":1.0,"y":1.0,"z":1.0},"pos":{"x":-1.07000017,"y":2.5,"z":0.5},"rot":{"x":0.0,"y":0.0,"z":0.0,"w":1.0}},{"tableId":0,"type":11,"size":{"x":1.0,"y":1.0,"z":1.0},"pos":{"x":-1.07000017,"y":2.5,"z":1.5},"rot":{"x":0.0,"y":0.0,"z":0.0,"w":1.0}},{"tableId":0,"type":11,"size":{"x":1.0,"y":1.0,"z":1.0},"pos":{"x":-2.07000017,"y":2.5,"z":0.5},"rot":{"x":0.0,"y":0.0,"z":0.0,"w":1.0}},{"tableId":0,"type":11,"size":{"x":1.0,"y":1.0,"z":1.0},"pos":{"x":-2.07000017,"y":2.5,"z":1.5},"rot":{"x":0.0,"y":0.0,"z":0.0,"w":1.0}},{"tableId":0,"type":11,"size":{"x":1.0,"y":1.0,"z":1.0},"pos":{"x":-1.07000017,"y":3.5,"z":0.5},"rot":{"x":0.0,"y":0.0,"z":0.0,"w":1.0}},{"tableId":0,"type":11,"size":{"x":1.0,"y":1.0,"z":1.0},"pos":{"x":-1.07000017,"y":3.5,"z":1.5},"rot":{"x":0.0,"y":0.0,"z":0.0,"w":1.0}},{"tableId":0,"type":11,"size":{"x":1.0,"y":1.0,"z":1.0},"pos":{"x":-2.07000017,"y":3.5,"z":0.5},"rot":{"x":0.0,"y":0.0,"z":0.0,"w":1.0}},{"tableId":0,"type":11,"size":{"x":1.0,"y":1.0,"z":1.0},"pos":{"x":-2.07000017,"y":3.5,"z":1.5},"rot":{"x":0.0,"y":0.0,"z":0.0,"w":1.0}},{"tableId":0,"type":11,"size":{"x":1.0,"y":1.0,"z":1.0},"pos":{"x":0.9299998,"y":0.5,"z":1.5},"rot":{"x":0.0,"y":0.0,"z":0.0,"w":1.0}},{"tableId":0,"type":11,"size":{"x":1.0,"y":1.0,"z":1.0},"pos":{"x":0.9299998,"y":0.5,"z":0.5},"rot":{"x":0.0,"y":0.0,"z":0.0,"w":1.0}},{"tableId":0,"type":11,"size":{"x":1.0,"y":1.0,"z":1.0},"pos":{"x":1.92999983,"y":0.5,"z":1.5},"rot":{"x":0.0,"y":0.0,"z":0.0,"w":1.0}},{"tableId":0,"type":11,"size":{"x":1.0,"y":1.0,"z":1.0},"pos":{"x":1.92999983,"y":0.5,"z":0.5},"rot":{"x":0.0,"y":0.0,"z":0.0,"w":1.0}},{"tableId":0,"type":11,"size":{"x":1.0,"y":1.0,"z":1.0},"pos":{"x":1.92999983,"y":1.5,"z":1.5},"rot":{"x":0.0,"y":0.0,"z":0.0,"w":1.0}},{"tableId":0,"type":11,"size":{"x":1.0,"y":1.0,"z":1.0},"pos":{"x":1.92999983,"y":1.5,"z":0.5},"rot":{"x":0.0,"y":0.0,"z":0.0,"w":1.0}},{"tableId":0,"type":11,"size":{"x":1.0,"y":1.0,"z":1.0},"pos":{"x":0.9299998,"y":1.5,"z":1.5},"rot":{"x":0.0,"y":0.0,"z":0.0,"w":1.0}},{"tableId":0,"type":11,"size":{"x":1.0,"y":1.0,"z":1.0},"pos":{"x":0.9299998,"y":1.5,"z":0.5},"rot":{"x":0.0,"y":0.0,"z":0.0,"w":1.0}},{"tableId":0,"type":11,"size":{"x":1.0,"y":1.0,"z":1.0},"pos":{"x":1.92999983,"y":2.5,"z":1.5},"rot":{"x":0.0,"y":0.0,"z":0.0,"w":1.0}},{"tableId":0,"type":11,"size":{"x":1.0,"y":1.0,"z":1.0},"pos":{"x":1.92999983,"y":2.5,"z":0.5},"rot":{"x":0.0,"y":0.0,"z":0.0,"w":1.0}},{"tableId":0,"type":11,"size":{"x":1.0,"y":1.0,"z":1.0},"pos":{"x":0.9299998,"y":2.5,"z":1.5},"rot":{"x":0.0,"y":0.0,"z":0.0,"w":1.0}},{"tableId":0,"type":11,"size":{"x":1.0,"y":1.0,"z":1.0},"pos":{"x":0.9299998,"y":2.5,"z":0.5},"rot":{"x":0.0,"y":0.0,"z":0.0,"w":1.0}},{"tableId":0,"type":11,"size":{"x":1.0,"y":1.0,"z":1.0},"pos":{"x":1.92999983,"y":3.5,"z":1.5},"rot":{"x":0.0,"y":0.0,"z":0.0,"w":1.0}},{"tableId":0,"type":11,"size":{"x":1.0,"y":1.0,"z":1.0},"pos":{"x":1.92999983,"y":3.5,"z":0.5},"rot":{"x":0.0,"y":0.0,"z":0.0,"w":1.0}},{"tableId":0,"type":11,"size":{"x":1.0,"y":1.0,"z":1.0},"pos":{"x":0.9299998,"y":3.5,"z":1.5},"rot":{"x":0.0,"y":0.0,"z":0.0,"w":1.0}},{"tableId":0,"type":11,"size":{"x":1.0,"y":1.0,"z":1.0},"pos":{"x":0.9299998,"y":3.5,"z":0.5},"rot":{"x":0.0,"y":0.0,"z":0.0,"w":1.0}}],"tables":[{"id":0,"pos":{"x":0.0,"y":2.9,"z":0.0},"rot":{"x":0.0,"y":0.0,"z":0.0,"w":1.0},"scl":{"x":1.0,"y":1.0,"z":1.0},"dim":{"x":9.14,"y":4.0,"z":0.0},"doRot":false,"rotSpd":0.0,"movH":false,"movHMin":0.0,"movHMax":0.0,"dirH":0,"movSpdH":0.0,"movV":false,"movVMin":0.0,"movVMax":0.0,"dirV":0,"movSpdV":0.0}],"blockers":[]}]}