{"levelIndex":297,"moveCount":26,"difficulty":1,"stages":[{"objects":[{"tableId":0,"type":21,"size":{"x":1.0,"y":2.0,"z":1.0},"pos":{"x":-1.18000007,"y":2.0,"z":-1.1505},"rot":{"x":0.0,"y":0.0,"z":0.0,"w":1.0}},{"tableId":0,"type":21,"size":{"x":1.0,"y":2.0,"z":1.0},"pos":{"x":0.01999998,"y":2.0,"z":-1.1505},"rot":{"x":0.0,"y":0.0,"z":0.0,"w":1.0}},{"tableId":0,"type":21,"size":{"x":1.0,"y":2.0,"z":1.0},"pos":{"x":1.22,"y":2.0,"z":-1.1505},"rot":{"x":0.0,"y":0.0,"z":0.0,"w":1.0}},{"tableId":0,"type":21,"size":{"x":1.0,"y":2.0,"z":1.0},"pos":{"x":-0.5680001,"y":2.0,"z":-0.0125000477},"rot":{"x":0.0,"y":0.0,"z":0.0,"w":1.0}},{"tableId":0,"type":21,"size":{"x":1.0,"y":2.0,"z":1.0},"pos":{"x":0.62,"y":2.0,"z":-0.0265001059},"rot":{"x":0.0,"y":0.0,"z":0.0,"w":1.0}},{"tableId":0,"type":21,"size":{"x":1.0,"y":2.0,"z":1.0},"pos":{"x":-0.5680001,"y":2.0,"z":-2.2435},"rot":{"x":0.0,"y":0.0,"z":0.0,"w":1.0}},{"tableId":0,"type":21,"size":{"x":1.0,"y":2.0,"z":1.0},"pos":{"x":0.62,"y":2.0,"z":-2.25750017},"rot":{"x":0.0,"y":0.0,"z":0.0,"w":1.0}},{"tableId":0,"type":21,"size":{"x":1.0,"y":2.0,"z":1.0},"pos":{"x":-1.80000007,"y":2.0,"z":0.0124998093},"rot":{"x":0.0,"y":0.0,"z":0.0,"w":1.0}},{"tableId":0,"type":21,"size":{"x":1.0,"y":2.0,"z":1.0},"pos":{"x":-2.98800015,"y":2.0,"z":0.0264999866},"rot":{"x":0.0,"y":0.0,"z":0.0,"w":1.0}},{"tableId":0,"type":21,"size":{"x":1.0,"y":2.0,"z":1.0},"pos":{"x":-1.80000007,"y":2.0,"z":2.24349976},"rot":{"x":0.0,"y":0.0,"z":0.0,"w":1.0}},{"tableId":0,"type":21,"size":{"x":1.0,"y":2.0,"z":1.0},"pos":{"x":-2.98800015,"y":2.0,"z":2.2575},"rot":{"x":0.0,"y":0.0,"z":0.0,"w":1.0}},{"tableId":0,"type":21,"size":{"x":1.0,"y":2.0,"z":1.0},"pos":{"x":-1.2,"y":2.0,"z":1.11949992},"rot":{"x":0.0,"y":0.0,"z":0.0,"w":1.0}},{"tableId":0,"type":21,"size":{"x":1.0,"y":2.0,"z":1.0},"pos":{"x":-2.4,"y":2.0,"z":1.11949992},"rot":{"x":0.0,"y":0.0,"z":0.0,"w":1.0}},{"tableId":0,"type":21,"size":{"x":1.0,"y":2.0,"z":1.0},"pos":{"x":-3.60000014,"y":2.0,"z":1.11949992},"rot":{"x":0.0,"y":0.0,"z":0.0,"w":1.0}},{"tableId":0,"type":21,"size":{"x":1.0,"y":2.0,"z":1.0},"pos":{"x":1.2,"y":2.0,"z":1.11949992},"rot":{"x":0.0,"y":0.0,"z":0.0,"w":1.0}},{"tableId":0,"type":21,"size":{"x":1.0,"y":2.0,"z":1.0},"pos":{"x":2.4,"y":2.0,"z":1.11949992},"rot":{"x":0.0,"y":0.0,"z":0.0,"w":1.0}},{"tableId":0,"type":21,"size":{"x":1.0,"y":2.0,"z":1.0},"pos":{"x":3.60000014,"y":2.0,"z":1.11949992},"rot":{"x":0.0,"y":0.0,"z":0.0,"w":1.0}},{"tableId":0,"type":21,"size":{"x":1.0,"y":2.0,"z":1.0},"pos":{"x":1.812,"y":2.0,"z":2.2575},"rot":{"x":0.0,"y":0.0,"z":0.0,"w":1.0}},{"tableId":0,"type":21,"size":{"x":1.0,"y":2.0,"z":1.0},"pos":{"x":3.0,"y":2.0,"z":2.24349976},"rot":{"x":0.0,"y":0.0,"z":0.0,"w":1.0}},{"tableId":0,"type":21,"size":{"x":1.0,"y":2.0,"z":1.0},"pos":{"x":1.812,"y":2.0,"z":0.0264999866},"rot":{"x":0.0,"y":0.0,"z":0.0,"w":1.0}},{"tableId":0,"type":21,"size":{"x":1.0,"y":2.0,"z":1.0},"pos":{"x":3.0,"y":2.0,"z":0.0124998093},"rot":{"x":0.0,"y":0.0,"z":0.0,"w":1.0}},{"tableId":0,"type":3,"size":{"x":1.0,"y":1.0,"z":1.0},"pos":{"x":0.01999998,"y":0.5,"z":-1.1505},"rot":{"x":0.0,"y":0.0,"z":0.0,"w":1.0}},{"tableId":0,"type":3,"size":{"x":1.0,"y":1.0,"z":1.0},"pos":{"x":-1.18000007,"y":0.5,"z":-1.1505},"rot":{"x":0.0,"y":0.0,"z":0.0,"w":1.0}},{"tableId":0,"type":3,"size":{"x":1.0,"y":1.0,"z":1.0},"pos":{"x":1.22,"y":0.5,"z":-1.1505},"rot":{"x":0.0,"y":0.0,"z":0.0,"w":1.0}},{"tableId":0,"type":3,"size":{"x":1.0,"y":1.0,"z":1.0},"pos":{"x":-0.5680001,"y":0.5,"z":-0.0125000477},"rot":{"x":0.0,"y":0.0,"z":0.0,"w":1.0}},{"tableId":0,"type":3,"size":{"x":1.0,"y":1.0,"z":1.0},"pos":{"x":0.62,"y":0.5,"z":-0.0265001059},"rot":{"x":0.0,"y":0.0,"z":0.0,"w":1.0}},{"tableId":0,"type":3,"size":{"x":1.0,"y":1.0,"z":1.0},"pos":{"x":-0.5680001,"y":0.5,"z":-2.24350023},"rot":{"x":0.0,"y":0.0,"z":0.0,"w":1.0}},{"tableId":0,"type":3,"size":{"x":1.0,"y":1.0,"z":1.0},"pos":{"x":0.62,"y":0.5,"z":-2.25750017},"rot":{"x":0.0,"y":0.0,"z":0.0,"w":1.0}},{"tableId":0,"type":3,"size":{"x":1.0,"y":1.0,"z":1.0},"pos":{"x":-1.80000007,"y":0.5,"z":0.0124998093},"rot":{"x":0.0,"y":0.0,"z":0.0,"w":1.0}},{"tableId":0,"type":3,"size":{"x":1.0,"y":1.0,"z":1.0},"pos":{"x":-2.98800015,"y":0.5,"z":0.0264997482},"rot":{"x":0.0,"y":0.0,"z":0.0,"w":1.0}},{"tableId":0,"type":3,"size":{"x":1.0,"y":1.0,"z":1.0},"pos":{"x":-1.80000007,"y":0.5,"z":2.24349976},"rot":{"x":0.0,"y":0.0,"z":0.0,"w":1.0}},{"tableId":0,"type":3,"size":{"x":1.0,"y":1.0,"z":1.0},"pos":{"x":-2.98800015,"y":0.5,"z":2.2575},"rot":{"x":0.0,"y":0.0,"z":0.0,"w":1.0}},{"tableId":0,"type":3,"size":{"x":1.0,"y":1.0,"z":1.0},"pos":{"x":-1.2,"y":0.5,"z":1.11949992},"rot":{"x":0.0,"y":0.0,"z":0.0,"w":1.0}},{"tableId":0,"type":3,"size":{"x":1.0,"y":1.0,"z":1.0},"pos":{"x":-3.60000014,"y":0.5,"z":1.11949992},"rot":{"x":0.0,"y":0.0,"z":0.0,"w":1.0}},{"tableId":0,"type":3,"size":{"x":1.0,"y":1.0,"z":1.0},"pos":{"x":-2.4,"y":0.5,"z":1.11949992},"rot":{"x":0.0,"y":0.0,"z":0.0,"w":1.0}},{"tableId":0,"type":3,"size":{"x":1.0,"y":1.0,"z":1.0},"pos":{"x":2.4,"y":0.5,"z":1.11949992},"rot":{"x":0.0,"y":0.0,"z":0.0,"w":1.0}},{"tableId":0,"type":3,"size":{"x":1.0,"y":1.0,"z":1.0},"pos":{"x":1.2,"y":0.5,"z":1.11949992},"rot":{"x":0.0,"y":0.0,"z":0.0,"w":1.0}},{"tableId":0,"type":3,"size":{"x":1.0,"y":1.0,"z":1.0},"pos":{"x":3.60000014,"y":0.5,"z":1.11949992},"rot":{"x":0.0,"y":0.0,"z":0.0,"w":1.0}},{"tableId":0,"type":3,"size":{"x":1.0,"y":1.0,"z":1.0},"pos":{"x":1.812,"y":0.5,"z":2.2575},"rot":{"x":0.0,"y":0.0,"z":0.0,"w":1.0}},{"tableId":0,"type":3,"size":{"x":1.0,"y":1.0,"z":1.0},"pos":{"x":3.0,"y":0.5,"z":2.24349976},"rot":{"x":0.0,"y":0.0,"z":0.0,"w":1.0}},{"tableId":0,"type":3,"size":{"x":1.0,"y":1.0,"z":1.0},"pos":{"x":1.812,"y":0.5,"z":0.0264997482},"rot":{"x":0.0,"y":0.0,"z":0.0,"w":1.0}},{"tableId":0,"type":3,"size":{"x":1.0,"y":1.0,"z":1.0},"pos":{"x":3.0,"y":0.5,"z":0.0124998093},"rot":{"x":0.0,"y":0.0,"z":0.0,"w":1.0}},{"tableId":0,"type":3,"size":{"x":1.0,"y":1.0,"z":1.0},"pos":{"x":-1.18000007,"y":3.5,"z":-1.1505},"rot":{"x":0.0,"y":0.0,"z":0.0,"w":1.0}},{"tableId":0,"type":3,"size":{"x":1.0,"y":1.0,"z":1.0},"pos":{"x":0.01999998,"y":3.5,"z":-1.1505},"rot":{"x":0.0,"y":0.0,"z":0.0,"w":1.0}},{"tableId":0,"type":3,"size":{"x":1.0,"y":1.0,"z":1.0},"pos":{"x":1.22,"y":3.5,"z":-1.1505},"rot":{"x":0.0,"y":0.0,"z":0.0,"w":1.0}},{"tableId":0,"type":3,"size":{"x":1.0,"y":1.0,"z":1.0},"pos":{"x":-0.568,"y":3.5,"z":-0.0125000477},"rot":{"x":0.0,"y":0.0,"z":0.0,"w":1.0}},{"tableId":0,"type":3,"size":{"x":1.0,"y":1.0,"z":1.0},"pos":{"x":0.62,"y":3.5,"z":-0.0265001059},"rot":{"x":0.0,"y":0.0,"z":0.0,"w":1.0}},{"tableId":0,"type":3,"size":{"x":1.0,"y":1.0,"z":1.0},"pos":{"x":-0.568,"y":3.5,"z":-2.2435},"rot":{"x":0.0,"y":0.0,"z":0.0,"w":1.0}},{"tableId":0,"type":3,"size":{"x":1.0,"y":1.0,"z":1.0},"pos":{"x":0.62,"y":3.5,"z":-2.25750017},"rot":{"x":0.0,"y":0.0,"z":0.0,"w":1.0}},{"tableId":0,"type":3,"size":{"x":1.0,"y":1.0,"z":1.0},"pos":{"x":-1.80000007,"y":3.5,"z":0.0124998093},"rot":{"x":0.0,"y":0.0,"z":0.0,"w":1.0}},{"tableId":0,"type":3,"size":{"x":1.0,"y":1.0,"z":1.0},"pos":{"x":-2.98800015,"y":3.5,"z":0.0264999866},"rot":{"x":0.0,"y":0.0,"z":0.0,"w":1.0}},{"tableId":0,"type":3,"size":{"x":1.0,"y":1.0,"z":1.0},"pos":{"x":-1.80000007,"y":3.5,"z":2.24349976},"rot":{"x":0.0,"y":0.0,"z":0.0,"w":1.0}},{"tableId":0,"type":3,"size":{"x":1.0,"y":1.0,"z":1.0},"pos":{"x":-2.98800015,"y":3.5,"z":2.2575},"rot":{"x":0.0,"y":0.0,"z":0.0,"w":1.0}},{"tableId":0,"type":3,"size":{"x":1.0,"y":1.0,"z":1.0},"pos":{"x":-1.2,"y":3.5,"z":1.11949992},"rot":{"x":0.0,"y":0.0,"z":0.0,"w":1.0}},{"tableId":0,"type":3,"size":{"x":1.0,"y":1.0,"z":1.0},"pos":{"x":-2.4,"y":3.5,"z":1.11949992},"rot":{"x":0.0,"y":0.0,"z":0.0,"w":1.0}},{"tableId":0,"type":3,"size":{"x":1.0,"y":1.0,"z":1.0},"pos":{"x":-3.60000014,"y":3.5,"z":1.11949992},"rot":{"x":0.0,"y":0.0,"z":0.0,"w":1.0}},{"tableId":0,"type":3,"size":{"x":1.0,"y":1.0,"z":1.0},"pos":{"x":1.2,"y":3.5,"z":1.11949992},"rot":{"x":0.0,"y":0.0,"z":0.0,"w":1.0}},{"tableId":0,"type":3,"size":{"x":1.0,"y":1.0,"z":1.0},"pos":{"x":2.4,"y":3.5,"z":1.11949992},"rot":{"x":0.0,"y":0.0,"z":0.0,"w":1.0}},{"tableId":0,"type":3,"size":{"x":1.0,"y":1.0,"z":1.0},"pos":{"x":3.60000014,"y":3.5,"z":1.11949992},"rot":{"x":0.0,"y":0.0,"z":0.0,"w":1.0}},{"tableId":0,"type":3,"size":{"x":1.0,"y":1.0,"z":1.0},"pos":{"x":1.812,"y":3.5,"z":2.2575},"rot":{"x":0.0,"y":0.0,"z":0.0,"w":1.0}},{"tableId":0,"type":3,"size":{"x":1.0,"y":1.0,"z":1.0},"pos":{"x":3.0,"y":3.5,"z":2.24349976},"rot":{"x":0.0,"y":0.0,"z":0.0,"w":1.0}},{"tableId":0,"type":3,"size":{"x":1.0,"y":1.0,"z":1.0},"pos":{"x":1.812,"y":3.5,"z":0.0264999866},"rot":{"x":0.0,"y":0.0,"z":0.0,"w":1.0}},{"tableId":0,"type":3,"size":{"x":1.0,"y":1.0,"z":1.0},"pos":{"x":3.0,"y":3.5,"z":0.0124998093},"rot":{"x":0.0,"y":0.0,"z":0.0,"w":1.0}},{"tableId":0,"type":41,"size":{"x":1.0,"y":2.0,"z":1.0},"pos":{"x":-1.18000007,"y":5.0,"z":-1.1505},"rot":{"x":0.0,"y":0.0,"z":0.0,"w":1.0}},{"tableId":0,"type":41,"size":{"x":1.0,"y":2.0,"z":1.0},"pos":{"x":0.01999998,"y":5.0,"z":-1.1505},"rot":{"x":0.0,"y":0.0,"z":0.0,"w":1.0}},{"tableId":0,"type":41,"size":{"x":1.0,"y":2.0,"z":1.0},"pos":{"x":1.22,"y":5.0,"z":-1.1505},"rot":{"x":0.0,"y":0.0,"z":0.0,"w":1.0}},{"tableId":0,"type":41,"size":{"x":1.0,"y":2.0,"z":1.0},"pos":{"x":-0.568,"y":5.0,"z":-0.0125000477},"rot":{"x":0.0,"y":0.0,"z":0.0,"w":1.0}},{"tableId":0,"type":41,"size":{"x":1.0,"y":2.0,"z":1.0},"pos":{"x":0.62,"y":5.0,"z":-0.0265001059},"rot":{"x":0.0,"y":0.0,"z":0.0,"w":1.0}},{"tableId":0,"type":41,"size":{"x":1.0,"y":2.0,"z":1.0},"pos":{"x":-0.568,"y":5.0,"z":-2.2435},"rot":{"x":0.0,"y":0.0,"z":0.0,"w":1.0}},{"tableId":0,"type":41,"size":{"x":1.0,"y":2.0,"z":1.0},"pos":{"x":0.62,"y":5.0,"z":-2.25750017},"rot":{"x":0.0,"y":0.0,"z":0.0,"w":1.0}},{"tableId":0,"type":41,"size":{"x":1.0,"y":2.0,"z":1.0},"pos":{"x":-1.80000007,"y":5.0,"z":0.0124998093},"rot":{"x":0.0,"y":0.0,"z":0.0,"w":1.0}},{"tableId":0,"type":41,"size":{"x":1.0,"y":2.0,"z":1.0},"pos":{"x":-2.98800015,"y":5.0,"z":0.0264999866},"rot":{"x":0.0,"y":0.0,"z":0.0,"w":1.0}},{"tableId":0,"type":41,"size":{"x":1.0,"y":2.0,"z":1.0},"pos":{"x":-1.80000007,"y":5.0,"z":2.24349976},"rot":{"x":0.0,"y":0.0,"z":0.0,"w":1.0}},{"tableId":0,"type":41,"size":{"x":1.0,"y":2.0,"z":1.0},"pos":{"x":-2.98800015,"y":5.0,"z":2.2575},"rot":{"x":0.0,"y":0.0,"z":0.0,"w":1.0}},{"tableId":0,"type":41,"size":{"x":1.0,"y":2.0,"z":1.0},"pos":{"x":-1.2,"y":5.0,"z":1.11949992},"rot":{"x":0.0,"y":0.0,"z":0.0,"w":1.0}},{"tableId":0,"type":41,"size":{"x":1.0,"y":2.0,"z":1.0},"pos":{"x":-2.4,"y":5.0,"z":1.11949992},"rot":{"x":0.0,"y":0.0,"z":0.0,"w":1.0}},{"tableId":0,"type":41,"size":{"x":1.0,"y":2.0,"z":1.0},"pos":{"x":-3.60000014,"y":5.0,"z":1.11949992},"rot":{"x":0.0,"y":0.0,"z":0.0,"w":1.0}},{"tableId":0,"type":41,"size":{"x":1.0,"y":2.0,"z":1.0},"pos":{"x":1.2,"y":5.0,"z":1.11949992},"rot":{"x":0.0,"y":0.0,"z":0.0,"w":1.0}},{"tableId":0,"type":41,"size":{"x":1.0,"y":2.0,"z":1.0},"pos":{"x":2.4,"y":5.0,"z":1.11949992},"rot":{"x":0.0,"y":0.0,"z":0.0,"w":1.0}},{"tableId":0,"type":41,"size":{"x":1.0,"y":2.0,"z":1.0},"pos":{"x":3.60000014,"y":5.0,"z":1.11949992},"rot":{"x":0.0,"y":0.0,"z":0.0,"w":1.0}},{"tableId":0,"type":41,"size":{"x":1.0,"y":2.0,"z":1.0},"pos":{"x":1.812,"y":5.0,"z":2.2575},"rot":{"x":0.0,"y":0.0,"z":0.0,"w":1.0}},{"tableId":0,"type":41,"size":{"x":1.0,"y":2.0,"z":1.0},"pos":{"x":3.0,"y":5.0,"z":2.24349976},"rot":{"x":0.0,"y":0.0,"z":0.0,"w":1.0}},{"tableId":0,"type":41,"size":{"x":1.0,"y":2.0,"z":1.0},"pos":{"x":1.812,"y":5.0,"z":0.0264999866},"rot":{"x":0.0,"y":0.0,"z":0.0,"w":1.0}},{"tableId":0,"type":41,"size":{"x":1.0,"y":2.0,"z":1.0},"pos":{"x":3.0,"y":5.0,"z":0.0124998093},"rot":{"x":0.0,"y":0.0,"z":0.0,"w":1.0}},{"tableId":0,"type":3,"size":{"x":1.0,"y":1.0,"z":1.0},"pos":{"x":-1.18000007,"y":6.49999952,"z":-1.1505},"rot":{"x":0.0,"y":0.0,"z":0.0,"w":1.0}},{"tableId":0,"type":3,"size":{"x":1.0,"y":1.0,"z":1.0},"pos":{"x":0.01999998,"y":6.49999952,"z":-1.1505},"rot":{"x":0.0,"y":0.0,"z":0.0,"w":1.0}},{"tableId":0,"type":3,"size":{"x":1.0,"y":1.0,"z":1.0},"pos":{"x":1.22,"y":6.49999952,"z":-1.1505},"rot":{"x":0.0,"y":0.0,"z":0.0,"w":1.0}},{"tableId":0,"type":3,"size":{"x":1.0,"y":1.0,"z":1.0},"pos":{"x":-0.568,"y":6.49999952,"z":-0.0125000477},"rot":{"x":0.0,"y":0.0,"z":0.0,"w":1.0}},{"tableId":0,"type":3,"size":{"x":1.0,"y":1.0,"z":1.0},"pos":{"x":0.62,"y":6.49999952,"z":-0.0265001059},"rot":{"x":0.0,"y":0.0,"z":0.0,"w":1.0}},{"tableId":0,"type":3,"size":{"x":1.0,"y":1.0,"z":1.0},"pos":{"x":-0.568,"y":6.49999952,"z":-2.2435},"rot":{"x":0.0,"y":0.0,"z":0.0,"w":1.0}},{"tableId":0,"type":3,"size":{"x":1.0,"y":1.0,"z":1.0},"pos":{"x":0.62,"y":6.49999952,"z":-2.25750017},"rot":{"x":0.0,"y":0.0,"z":0.0,"w":1.0}},{"tableId":0,"type":3,"size":{"x":1.0,"y":1.0,"z":1.0},"pos":{"x":-1.80000007,"y":6.49999952,"z":0.0124998093},"rot":{"x":0.0,"y":0.0,"z":0.0,"w":1.0}},{"tableId":0,"type":3,"size":{"x":1.0,"y":1.0,"z":1.0},"pos":{"x":-2.98800015,"y":6.49999952,"z":0.0264999866},"rot":{"x":0.0,"y":0.0,"z":0.0,"w":1.0}},{"tableId":0,"type":3,"size":{"x":1.0,"y":1.0,"z":1.0},"pos":{"x":-1.80000007,"y":6.49999952,"z":2.24349976},"rot":{"x":0.0,"y":0.0,"z":0.0,"w":1.0}},{"tableId":0,"type":3,"size":{"x":1.0,"y":1.0,"z":1.0},"pos":{"x":-2.98800015,"y":6.49999952,"z":2.2575},"rot":{"x":0.0,"y":0.0,"z":0.0,"w":1.0}},{"tableId":0,"type":3,"size":{"x":1.0,"y":1.0,"z":1.0},"pos":{"x":-1.2,"y":6.49999952,"z":1.11949992},"rot":{"x":0.0,"y":0.0,"z":0.0,"w":1.0}},{"tableId":0,"type":3,"size":{"x":1.0,"y":1.0,"z":1.0},"pos":{"x":-2.4,"y":6.49999952,"z":1.11949992},"rot":{"x":0.0,"y":0.0,"z":0.0,"w":1.0}},{"tableId":0,"type":3,"size":{"x":1.0,"y":1.0,"z":1.0},"pos":{"x":-3.60000014,"y":6.49999952,"z":1.11949992},"rot":{"x":0.0,"y":0.0,"z":0.0,"w":1.0}},{"tableId":0,"type":3,"size":{"x":1.0,"y":1.0,"z":1.0},"pos":{"x":1.2,"y":6.49999952,"z":1.11949992},"rot":{"x":0.0,"y":0.0,"z":0.0,"w":1.0}},{"tableId":0,"type":3,"size":{"x":1.0,"y":1.0,"z":1.0},"pos":{"x":2.4,"y":6.49999952,"z":1.11949992},"rot":{"x":0.0,"y":0.0,"z":0.0,"w":1.0}},{"tableId":0,"type":3,"size":{"x":1.0,"y":1.0,"z":1.0},"pos":{"x":3.60000014,"y":6.49999952,"z":1.11949992},"rot":{"x":0.0,"y":0.0,"z":0.0,"w":1.0}},{"tableId":0,"type":3,"size":{"x":1.0,"y":1.0,"z":1.0},"pos":{"x":1.812,"y":6.49999952,"z":2.2575},"rot":{"x":0.0,"y":0.0,"z":0.0,"w":1.0}},{"tableId":0,"type":3,"size":{"x":1.0,"y":1.0,"z":1.0},"pos":{"x":3.0,"y":6.49999952,"z":2.24349976},"rot":{"x":0.0,"y":0.0,"z":0.0,"w":1.0}},{"tableId":0,"type":3,"size":{"x":1.0,"y":1.0,"z":1.0},"pos":{"x":1.812,"y":6.49999952,"z":0.0264999866},"rot":{"x":0.0,"y":0.0,"z":0.0,"w":1.0}},{"tableId":0,"type":3,"size":{"x":1.0,"y":1.0,"z":1.0},"pos":{"x":3.0,"y":6.49999952,"z":0.0124998093},"rot":{"x":0.0,"y":0.0,"z":0.0,"w":1.0}},{"tableId":0,"type":21,"size":{"x":1.0,"y":2.0,"z":1.0},"pos":{"x":-1.18000007,"y":7.99999952,"z":-1.1505},"rot":{"x":0.0,"y":0.0,"z":0.0,"w":1.0}},{"tableId":0,"type":21,"size":{"x":1.0,"y":2.0,"z":1.0},"pos":{"x":0.01999998,"y":7.99999952,"z":-1.1505},"rot":{"x":0.0,"y":0.0,"z":0.0,"w":1.0}},{"tableId":0,"type":21,"size":{"x":1.0,"y":2.0,"z":1.0},"pos":{"x":1.22,"y":7.99999952,"z":-1.1505},"rot":{"x":0.0,"y":0.0,"z":0.0,"w":1.0}},{"tableId":0,"type":21,"size":{"x":1.0,"y":2.0,"z":1.0},"pos":{"x":-0.568,"y":7.99999952,"z":-0.0125000477},"rot":{"x":0.0,"y":0.0,"z":0.0,"w":1.0}},{"tableId":0,"type":21,"size":{"x":1.0,"y":2.0,"z":1.0},"pos":{"x":0.62,"y":7.99999952,"z":-0.0265001059},"rot":{"x":0.0,"y":0.0,"z":0.0,"w":1.0}},{"tableId":0,"type":21,"size":{"x":1.0,"y":2.0,"z":1.0},"pos":{"x":-0.568,"y":7.99999952,"z":-2.2435},"rot":{"x":0.0,"y":0.0,"z":0.0,"w":1.0}},{"tableId":0,"type":21,"size":{"x":1.0,"y":2.0,"z":1.0},"pos":{"x":0.62,"y":7.99999952,"z":-2.25750017},"rot":{"x":0.0,"y":0.0,"z":0.0,"w":1.0}},{"tableId":0,"type":21,"size":{"x":1.0,"y":2.0,"z":1.0},"pos":{"x":-1.80000007,"y":7.99999952,"z":0.0124998093},"rot":{"x":0.0,"y":0.0,"z":0.0,"w":1.0}},{"tableId":0,"type":21,"size":{"x":1.0,"y":2.0,"z":1.0},"pos":{"x":-2.98800015,"y":7.99999952,"z":0.0264999866},"rot":{"x":0.0,"y":0.0,"z":0.0,"w":1.0}},{"tableId":0,"type":21,"size":{"x":1.0,"y":2.0,"z":1.0},"pos":{"x":-1.80000007,"y":7.99999952,"z":2.24349976},"rot":{"x":0.0,"y":0.0,"z":0.0,"w":1.0}},{"tableId":0,"type":21,"size":{"x":1.0,"y":2.0,"z":1.0},"pos":{"x":-2.98800015,"y":7.99999952,"z":2.2575},"rot":{"x":0.0,"y":0.0,"z":0.0,"w":1.0}},{"tableId":0,"type":21,"size":{"x":1.0,"y":2.0,"z":1.0},"pos":{"x":-1.2,"y":7.99999952,"z":1.11949992},"rot":{"x":0.0,"y":0.0,"z":0.0,"w":1.0}},{"tableId":0,"type":21,"size":{"x":1.0,"y":2.0,"z":1.0},"pos":{"x":-2.4,"y":7.99999952,"z":1.11949992},"rot":{"x":0.0,"y":0.0,"z":0.0,"w":1.0}},{"tableId":0,"type":21,"size":{"x":1.0,"y":2.0,"z":1.0},"pos":{"x":-3.60000014,"y":7.99999952,"z":1.11949992},"rot":{"x":0.0,"y":0.0,"z":0.0,"w":1.0}},{"tableId":0,"type":21,"size":{"x":1.0,"y":2.0,"z":1.0},"pos":{"x":1.2,"y":7.99999952,"z":1.11949992},"rot":{"x":0.0,"y":0.0,"z":0.0,"w":1.0}},{"tableId":0,"type":21,"size":{"x":1.0,"y":2.0,"z":1.0},"pos":{"x":2.4,"y":7.99999952,"z":1.11949992},"rot":{"x":0.0,"y":0.0,"z":0.0,"w":1.0}},{"tableId":0,"type":21,"size":{"x":1.0,"y":2.0,"z":1.0},"pos":{"x":3.60000014,"y":7.99999952,"z":1.11949992},"rot":{"x":0.0,"y":0.0,"z":0.0,"w":1.0}},{"tableId":0,"type":21,"size":{"x":1.0,"y":2.0,"z":1.0},"pos":{"x":1.812,"y":7.99999952,"z":2.2575},"rot":{"x":0.0,"y":0.0,"z":0.0,"w":1.0}},{"tableId":0,"type":21,"size":{"x":1.0,"y":2.0,"z":1.0},"pos":{"x":3.0,"y":7.99999952,"z":2.24349976},"rot":{"x":0.0,"y":0.0,"z":0.0,"w":1.0}},{"tableId":0,"type":21,"size":{"x":1.0,"y":2.0,"z":1.0},"pos":{"x":1.812,"y":7.99999952,"z":0.0264999866},"rot":{"x":0.0,"y":0.0,"z":0.0,"w":1.0}},{"tableId":0,"type":21,"size":{"x":1.0,"y":2.0,"z":1.0},"pos":{"x":3.0,"y":7.99999952,"z":0.0124998093},"rot":{"x":0.0,"y":0.0,"z":0.0,"w":1.0}}],"tables":[{"id":0,"pos":{"x":0.0,"y":2.9,"z":0.0},"rot":{"x":0.0,"y":0.0,"z":0.0,"w":1.0},"scl":{"x":1.0,"y":1.0,"z":1.0},"dim":{"x":8.2,"y":5.515,"z":0.0},"doRot":false,"rotSpd":0.0,"movH":false,"movHMin":0.0,"movHMax":0.0,"dirH":0,"movSpdH":0.0,"movV":false,"movVMin":0.0,"movVMax":0.0,"dirV":0,"movSpdV":0.0}],"blockers":[]}]}